.github/screenshots/graph.png
.github/screenshots/graph2.png
LICENSE
vt2m/__init__.py
vt2m/lib/__init__.py
vt2m/lib/lib.py
vt2m/lib/output.py
vt2m/main.py
vt2m/subcommands/notifications.py
vt2m/subcommands/retrohunts.py
vt2m-0.1.17.dist-info/LICENSE
vt2m-0.1.17.dist-info/METADATA
vt2m-0.1.17.dist-info/WHEEL
vt2m-0.1.17.dist-info/entry_points.txt
vt2m-0.1.17.dist-info/RECORD
