Metadata-Version: 2.1
Name: vt2m
Version: 0.1.17
Summary: Automatically import results from VirusTotal queries into MISP objects
Home-page: https://github.com/3c7/vt2m
License: MIT
Author: 3c7
Author-email: 3c7@posteo.de
Requires-Python: >=3.8,<4.0
Classifier: Development Status :: 4 - Beta
Classifier: Environment :: Console
Classifier: Intended Audience :: Information Technology
Classifier: Intended Audience :: Science/Research
Classifier: Intended Audience :: System Administrators
Classifier: License :: OSI Approved :: MIT License
Classifier: Operating System :: OS Independent
Classifier: Programming Language :: Python :: 3
Classifier: Programming Language :: Python :: 3.8
Classifier: Programming Language :: Python :: 3.9
Classifier: Programming Language :: Python :: 3.10
Classifier: Programming Language :: Python :: 3.11
Classifier: Programming Language :: Python :: 3.12
Classifier: Programming Language :: Python :: 3 :: Only
Classifier: Topic :: Security
Classifier: Topic :: Utilities
Requires-Dist: pymisp (>=2.4.182,<3.0.0)
Requires-Dist: requests (>=2.27.1,<3.0.0)
Requires-Dist: rich (>=13.3.5,<14.0.0)
Requires-Dist: typer (>=0.9.0,<0.10.0)
Requires-Dist: vt-py (>=0.18.0,<0.19.0)
Project-URL: Repository, https://github.com/3c7/vt2m
